{
  "parameters": [
    {
      "name": "data-tchmi-startbool",
      "displayName": "StartBool",
      "visible": true,
      "type": "tchmi:general#/definitions/BOOL",
      "category": "Do Not Set",
      "description": "",
      "requiredOnCompile": false,
      "readOnly": false,
      "bindable": true,
      "heritable": true,
      "propertyName": "StartBool",
      "propertySetterName": "setStartBool",
      "propertyGetterName": "getStartBool"
    },
    {
      "name": "data-tchmi-timetorun",
      "displayName": "TimeToRun",
      "visible": true,
      "type": "tchmi:general#/definitions/INT",
      "category": "",
      "description": "How long the overlay should be displayed",
      "defaultValue": 30,
      "defaultValueInternal": 30,
      "requiredOnCompile": false,
      "readOnly": false,
      "bindable": true,
      "heritable": true,
      "propertyName": "TimeToRun",
      "propertySetterName": "setTimeToRun",
      "propertyGetterName": "getTimeToRun"
    },
    {
      "name": "data-tchmi-this",
      "displayName": "This",
      "visible": true,
      "type": "tchmi:framework#/definitions/Control",
      "category": "",
      "description": "Binding to this control instance",
      "requiredOnCompile": false,
      "readOnly": false,
      "bindable": true,
      "heritable": true,
      "propertyName": "This",
      "propertySetterName": "setThis",
      "propertyGetterName": "getThis"
    },
    {
      "name": "data-tchmi-timeleft",
      "displayName": "TimeLeft",
      "visible": true,
      "type": "tchmi:general#/definitions/INT",
      "category": "Do Not Set",
      "description": "",
      "defaultValue": 0,
      "defaultValueInternal": 0,
      "requiredOnCompile": false,
      "readOnly": false,
      "bindable": true,
      "heritable": true,
      "propertyName": "TimeLeft",
      "propertySetterName": "setTimeLeft",
      "propertyGetterName": "getTimeLeft"
    },
    {
      "name": "data-tchmi-fontsize",
      "displayName": "FontSize",
      "visible": true,
      "type": "tchmi:general#/definitions/INT",
      "category": "",
      "description": "",
      "defaultValue": 16,
      "defaultValueInternal": 16,
      "requiredOnCompile": false,
      "readOnly": false,
      "bindable": true,
      "heritable": true,
      "propertyName": "FontSize",
      "propertySetterName": "setFontSize",
      "propertyGetterName": "getFontSize"
    },
    {
      "name": "data-tchmi-visible",
      "displayName": "Visible",
      "visible": true,
      "type": "tchmi:general#/definitions/BOOL",
      "category": "",
      "description": "",
      "defaultValue": true,
      "defaultValueInternal": true,
      "requiredOnCompile": false,
      "readOnly": false,
      "bindable": true,
      "heritable": true,
      "propertyName": "Visible",
      "propertySetterName": "setVisible",
      "propertyGetterName": "getVisible"
    }
  ],
  "virtualRights": [],
  "$schema": "C:/TwinCAT/Functions/TE2000-HMI-Engineering/Infrastructure/TcHmiFramework/Latest/Schema/UserControlConfig.Schema.json",
  "description": ""
}